pytest_html_merger/__init__.py
pytest_html_merger/__main__.py
pytest_html_merger/main.py
pytest_html_merger/version.py
pytest_html_merger-0.0.10.dist-info/LICENSE.txt
pytest_html_merger-0.0.10.dist-info/METADATA
pytest_html_merger-0.0.10.dist-info/WHEEL
pytest_html_merger-0.0.10.dist-info/entry_points.txt
pytest_html_merger-0.0.10.dist-info/top_level.txt
pytest_html_merger-0.0.10.dist-info/RECORD
